odoo/addons/geoengine_partner/README.rst
odoo/addons/geoengine_partner/__init__.py
odoo/addons/geoengine_partner/__manifest__.py
odoo/addons/geoengine_partner/i18n/geoengine_partner.pot
odoo/addons/geoengine_partner/models/__init__.py
odoo/addons/geoengine_partner/models/partner.py
odoo/addons/geoengine_partner/static/description/icon.png
odoo/addons/geoengine_partner/views/partner.xml
odoo12_addon_geoengine_partner-12.0.1.0.0.99.dev2.dist-info/METADATA
odoo12_addon_geoengine_partner-12.0.1.0.0.99.dev2.dist-info/WHEEL
odoo12_addon_geoengine_partner-12.0.1.0.0.99.dev2.dist-info/top_level.txt
odoo12_addon_geoengine_partner-12.0.1.0.0.99.dev2.dist-info/RECORD
